ls_buildtools/__init__.py
ls_buildtools/exceptions.py
ls_buildtools/protect.py
ls_buildtools/protector_config.py
ls_buildtools/utilities.py
ls_buildtools/_integration/__init__.py
ls_buildtools/_integration/hatchling.py
ls_buildtools/_integration/setuptools.py
ls_buildtools/_protections/__init__.py
ls_buildtools/_protections/encryption.py
ls_buildtools/_protections/global_filter.py
ls_buildtools/_protections/obfuscation.py
ls_buildtools-0.1.5.dist-info/METADATA
ls_buildtools-0.1.5.dist-info/WHEEL
ls_buildtools-0.1.5.dist-info/entry_points.txt
ls_buildtools-0.1.5.dist-info/RECORD
